docsCheck/__init__.py
docsCheck/__main__.py
docsCheck/Aspose.WordsforPythonvia.NET.lic
docsCheck/checker.py
docsCheck/runners.py
docsCheck/utils.py
docscheck-0.1.1.dist-info/entry_points.txt
docscheck-0.1.1.dist-info/METADATA
docscheck-0.1.1.dist-info/WHEEL
docscheck-0.1.1.dist-info/RECORD
