Metadata-Version: 2.1
Name: docsCheck
Version: 0.1.1
Summary: 
Author: Dmitry Proskurin
Author-email: proskurin.dima16@gmail.com
Requires-Python: >=3.8,<3.12
Classifier: Programming Language :: Python :: 3
Classifier: Programming Language :: Python :: 3.8
Classifier: Programming Language :: Python :: 3.9
Classifier: Programming Language :: Python :: 3.10
Classifier: Programming Language :: Python :: 3.11
Requires-Dist: aspose-words (==24.*)
Requires-Dist: prettytable (>=3.10.0,<4.0.0)
